CPU/shifter.vhdl
LIBRARY IEEE;
USE IEEE.STD_LOGIC_1164.ALL;

-- ARM processor Shifter

ENTITY Shifter IS 
    PORT(
        shift_lsl : in Std_Logic;
        shift_lsr : in Std_Logic;
        shift_asr : in Std_Logic;
        shift_ror : in Std_Logic;
        shift_rrx : in Std_Logic;
        shift_val : in Std_Logic_Vector(4 downto 0);    -- Shift value

        din       : in Std_Logic_Vector(31 downto 0);   -- data in
        cin       : in Std_Logic;                       -- carry in

        dout      : out Std_Logic_Vector(31 downto 0);  -- data out
        cout      : out Std_Logic;                      -- carry out
    
    -- global interface
        vdd       : in bit;
        vss       : in bit
    );
END Shifter;

ARCHITECTURE archi OF Shifter IS 

    signal dout_s1  : Std_Logic_Vector(31 downto 0);     -- Shift 1
    signal cout_s1  : Std_Logic;
    signal dout_s2  : Std_Logic_Vector(31 downto 0);     -- Shift 2
    signal cout_s2  : Std_Logic;
    signal dout_s4  : Std_Logic_Vector(31 downto 0);     -- Shift 4
    signal cout_s4  : Std_Logic;
    signal dout_s8  : Std_Logic_Vector(31 downto 0);     -- Shift 8
    signal cout_s8  : Std_Logic;
    signal dout_s16 : Std_Logic_Vector(31 downto 0);     -- Shift 16
    signal cout_s16 : Std_Logic;

BEGIN 
    ----------------------------------------------------- Shift 1 -----------------------------------------------------
    dout_s1(30 downto 1)    <=  din(31 downto 2)    when ((shift_lsr = '1' or shift_asr = '1' or shift_ror = '1')    -- LSR, ASR, ROR
                                                        and (shift_val(0) = '1')) else 
                                din(29 downto 0)    when ((shift_lsl = '1')                                          -- LSL 
                                                        and (shift_val(0) = '1')) else
                                din(30 downto 1)    when (shift_val(0) = '0');                                      -- No shift 1
    dout_s1(0)              <=  din(1)              when ((shift_lsr = '1' or shift_asr = '1' or shift_ror = '1')    -- LSR, ASR, ROR
                                                        and (shift_val(0) = '1')) else                            
                                '0'                 when ((shift_lsl = '1')                                         -- LSL
                                                        and (shift_val(0) = '1')) else
                                din(0)              when (shift_val(0) = '0');                                      -- No shift 1
    dout_s1(31)             <=  '0'                 when ((shift_lsr = '1')                                          -- LSR
                                                        and (shift_val(0) = '1')) else 
                                din(31)             when ((shift_asr = '1')                                          -- ASR 
                                                        and (shift_val(0) = '1')) else 
                                din(0)              when ((shift_ror = '1')                                          -- ROR
                                                        and (shift_val(0) = '1')) else
                                din(30)             when ((shift_lsl = '1')                                          -- LSL
                                                        and (shift_val(0) = '1')) else 
                                din(31)             when (shift_val(0) = '0');                                      -- No shift 1
    cout_s1                 <=  din(0)              when ((shift_lsr = '1' or shift_asr = '1')                       -- LSR, ASR 
                                                        and (shift_val(0) = '1')) else 
                                din(1)              when ((shift_ror = '1')                                          -- ROR 
                                                        and (shift_val(0) = '1')) else 
                                din(31)             when ((shift_lsl = '1')                                          -- LSL 
                                                        and (shift_val(0) = '1')) else
                                cin                 when (shift_val(0) = '0');                                      -- No shift 1

    ----------------------------------------------------- Shift 2 -----------------------------------------------------
    dout_s2(29 downto 2)    <=  dout_s1(31 downto 4)when ((shift_lsr = '1' or shift_asr = '1' or shift_ror = '1')    -- LSR, ASR, ROR
                                                        and (shift_val(1) = '1')) else 
                                dout_s1(27 downto 0)when ((shift_lsl = '1')                                          -- LSL 
                                                        and (shift_val(1) = '1')) else
                                dout_s1(29 downto 2)when (shift_val(1) = '0');                                      -- No shift 2
    dout_s2(1 downto 0)     <=  dout_s1(3 downto 2) when ((shift_lsr = '1' or shift_asr = '1' or shift_ror = '1')    -- LSR, ASR, ROR
                                                        and (shift_val(1) = '1')) else                            
                                "00"                when ((shift_lsl = '1')                                          -- LSL
                                                        and (shift_val(1) = '1')) else
                                dout_s1(1 downto 0) when (shift_val(1) = '0');                                      -- No shift 2
    dout_s2(31 downto 30)   <=  "00"                when ((shift_lsr = '1')                                          -- LSR
                                                        and (shift_val(1) = '1')) else 
                                dout_s1(31)&dout_s1(31) 
                                                    when ((shift_asr = '1')                                          -- ASR 
                                                        and (shift_val(1) = '1')) else 
                                dout_s1(1 downto 0) when ((shift_ror = '1')                                          -- ROR
                                                        and (shift_val(1) = '1')) else
                                dout_s1(29 downto 28)
                                                    when ((shift_lsl = '1')                                          -- LSL
                                                        and (shift_val(1) = '1')) else 
                                dout_s1(31 downto 30)   
                                                    when (shift_val(1) = '0');                                      -- No shift 2
    cout_s2                 <=  dout_s1(1)          when ((shift_lsr = '1' or shift_asr = '1')                       -- LSR, ASR 
                                                        and (shift_val(1) = '1')) else 
                                dout_s1(2)          when ((shift_ror = '1')                                          -- ROR 
                                                        and (shift_val(1) = '1')) else 
                                dout_s1(30)         when ((shift_lsl = '1')                                          -- LSL 
                                                        and (shift_val(1) = '1')) else
                                cout_s1             when (shift_val(1) = '0');                                      -- No shift 2
    
    ----------------------------------------------------- Shift 4 -----------------------------------------------------
    dout_s4(27 downto 4)    <=  dout_s2(31 downto 8)when ((shift_lsr = '1' or shift_asr = '1' or shift_ror = '1')    -- LSR, ASR, ROR
                                                        and (shift_val(2) = '1')) else 
                                dout_s2(23 downto 0)when ((shift_lsl = '1')                                          -- LSL 
                                                        and (shift_val(2) = '1')) else
                                dout_s2(27 downto 4)when (shift_val(2) = '0');                                      -- No shift 4
    dout_s4(3 downto 0)     <=  dout_s2(7 downto 4) when ((shift_lsr = '1' or shift_asr = '1' or shift_ror = '1')    -- LSR, ASR, ROR
                                                        and (shift_val(2) = '1')) else                            
                                "0000"              when ((shift_lsl = '1')                                          -- LSL
                                                        and (shift_val(2) = '1')) else
                                dout_s2(3 downto 0) when (shift_val(2) = '0');                                      -- No shift 4
    dout_s4(31 downto 28)   <=  "0000"              when ((shift_lsr = '1')                                          -- LSR
                                                        and (shift_val(2) = '1')) else 
                                dout_s2(31)&dout_s2(31)&dout_s2(31)&dout_s2(31)
                                                    when ((shift_asr = '1')                                          -- ASR 
                                                        and (shift_val(2) = '1')) else 
                                dout_s2(3 downto 0) when ((shift_ror = '1')                                          -- ROR
                                                        and (shift_val(2) = '1')) else
                                dout_s2(27 downto 24)   
                                                    when ((shift_lsl = '1')                                          -- LSL
                                                        and (shift_val(2) = '1')) else 
                                dout_s2(31 downto 28)   
                                                    when (shift_val(2) = '0');                                      -- No shift 4
    cout_s4                 <=  dout_s2(3)          when ((shift_lsr = '1' or shift_asr = '1')                       -- LSR, ASR 
                                                        and (shift_val(2) = '1')) else 
                                dout_s2(4)          when ((shift_ror = '1')                                          -- ROR 
                                                        and (shift_val(2) = '1')) else 
                                dout_s2(28)         when ((shift_lsl = '1')                                          -- LSL 
                                                        and (shift_val(2) = '1')) else
                                cout_s2             when (shift_val(2) = '0');                                      -- No shift 4                        
                        
    ----------------------------------------------------- Shift 8 -----------------------------------------------------
    dout_s8(23 downto 8)    <=  dout_s4(31 downto 16)
                                                    when ((shift_lsr = '1' or shift_asr = '1' or shift_ror = '1')    -- LSR, ASR, ROR
                                                        and (shift_val(3) = '1')) else 
                                dout_s4(15 downto 0)when ((shift_lsl = '1')                                          -- LSL 
                                                        and (shift_val(3) = '1')) else
                                dout_s4(23 downto 8)when (shift_val(3) = '0');                                      -- No shift 8
    dout_s8(7 downto 0)     <=  dout_s4(15 downto 8)when ((shift_lsr = '1' or shift_asr = '1' or shift_ror = '1')    -- LSR, ASR, ROR
                                                        and (shift_val(3) = '1')) else                            
                                "00000000"          when ((shift_lsl = '1')                                          -- LSL
                                                        and (shift_val(3) = '1')) else
                                dout_s4(7 downto 0) when (shift_val(3) = '0');                                      -- No shift 8
    dout_s8(31 downto 24)   <=  "00000000"          when ((shift_lsr = '1')                                          -- LSR
                                                        and (shift_val(3) = '1')) else 
                                dout_s4(31)&dout_s4(31)&dout_s4(31)&dout_s4(31)&dout_s4(31)&dout_s4(31)&dout_s4(31)&dout_s4(31)
                                                    when ((shift_asr = '1')                                          -- ASR 
                                                        and (shift_val(3) = '1')) else 
                                dout_s4(7 downto 0) when ((shift_ror = '1')                                          -- ROR
                                                        and (shift_val(3) = '1')) else
                                dout_s4(23 downto 16)   
                                                    when ((shift_lsl = '1')                                          -- LSL
                                                        and (shift_val(3) = '1')) else 
                                dout_s4(31 downto 24)   
                                                    when (shift_val(3) = '0');                                      -- No shift 8
    cout_s8                 <=  dout_s4(7)          when ((shift_lsr = '1' or shift_asr = '1')                       -- LSR, ASR 
                                                        and (shift_val(3) = '1')) else 
                                dout_s4(8)          when ((shift_ror = '1')                                          -- ROR 
                                                        and (shift_val(3) = '1')) else 
                                dout_s4(24)         when ((shift_lsl = '1')                                          -- LSL 
                                                        and (shift_val(3) = '1')) else
                                cout_s4             when (shift_val(3) = '0');                                      -- No shift 8
    
    ----------------------------------------------------- Shift 16 -----------------------------------------------------
    dout_s16(15 downto 0)   <=  dout_s8(31 downto 16)   
                                                    when ((shift_lsr = '1' or shift_asr = '1' or shift_ror = '1')    -- LSR, ASR, ROR
                                                        and (shift_val(4) = '1')) else 
                                "0000000000000000"  when ((shift_lsl = '1')                                          -- LSL 
                                                        and (shift_val(4) = '1')) else
                                dout_s8(15 downto 0)when (shift_val(4) = '0');                                      -- No shift 16
    dout_s16(31 downto 16)  <=  "0000000000000000"  when ((shift_lsr = '1')                                          -- LSR
                                                        and (shift_val(4) = '1')) else 
                                dout_s8(31)&dout_s8(31)&dout_s8(31)&dout_s8(31)&dout_s8(31)&dout_s8(31)&dout_s8(31)&dout_s8(31)&dout_s8(31)&dout_s8(31)&dout_s8(31)&dout_s8(31)&dout_s8(31)&dout_s8(31)&dout_s8(31)&dout_s8(31)
                                                    when ((shift_asr = '1')                                          -- ASR 
                                                        and (shift_val(4) = '1')) else 
                                dout_s8(15 downto 0)when ((shift_ror = '1' or shift_lsl = '1')                       -- ROR, LSL
                                                        and (shift_val(4) = '1')) else
                                dout_s8(31 downto 16)   
                                                    when (shift_val(4) = '0');                                      -- No shift 16
    cout_s16                <=  dout_s8(15)         when ((shift_lsr = '1' or shift_asr = '1')                       -- LSR, ASR 
                                                        and (shift_val(4) = '1')) else 
                                dout_s8(16)         when ((shift_ror = '1')                                          -- ROR 
                                                        and (shift_val(4) = '1')) else 
                                dout_s8(16)         when ((shift_lsl = '1')                                          -- LSL 
                                                        and (shift_val(4) = '1')) else
                                cout_s8             when (shift_val(4) = '0');                                      -- No shift 16
    
    -- Mise a jour des sorties 
    dout <= dout_s16;
    cout <= cout_s16;

END archi;

Shifter/tb_shifter.vhdl
LIBRARY IEEE;
USE IEEE.STD_LOGIC_1164.ALL;

-- Testbench for ARM Shifter

ENTITY tb_Shifter IS 
END tb_Shifter;

ARCHITECTURE behavior OF tb_Shifter IS 
    COMPONENT Shifter
        PORT(
            shift_lsl : in Std_Logic;
            shift_lsr : in Std_Logic;
            shift_asr : in Std_Logic;
            shift_ror : in Std_Logic;
            shift_rrx : in Std_Logic;
            shift_val : in Std_Logic_Vector(4 downto 0);
            din       : in Std_Logic_Vector(31 downto 0);   -- data in
            cin       : in Std_Logic;                       -- carry in
            dout      : out Std_Logic_Vector(31 downto 0);  -- data out
            cout      : out Std_Logic;                      -- carry out
            vdd       : in bit;
            vss       : in bit
        );
    END COMPONENT;

    signal LSL_tb:          Std_Logic :='0';
    signal LSR_tb:          Std_Logic :='0';
    signal ASR_tb:          Std_Logic :='0';
    signal ROR_tb:          Std_Logic :='0';
    signal RRX_tb:          Std_Logic :='0';
    signal shift_val_tb:    Std_Logic_Vector(4 downto 0):="00000";
    signal din_tb:          Std_Logic_Vector(31 downto 0):="00000011111111110000111110000000";
    signal cin_tb:          Std_Logic :='0';
    signal dout_tb:         Std_Logic_Vector(31 downto 0);
    signal cout_tb:         Std_Logic;
    signal vdd_tb:          bit;
    signal vss_tb:          bit;

BEGIN 
    uut: Shifter PORT MAP(shift_lsl => LSL_tb, shift_lsr => LSR_tb, shift_asr => ASR_tb, shift_ror => ROR_tb, shift_rrx => RRX_tb,
                          shift_val => shift_val_tb, din => din_tb, cin=>cin_tb, 
                          dout => dout_tb, cout => cout_tb,
                          vdd => vdd_tb, vss => vss_tb);
    
    LSL_tb <= '1' after 50 ns, '0' after 100 ns, '0' after 150 ns, '1' after 300 ns, '0' after 350 ns; 
    LSR_tb <= '0' after 50 ns, '1' after 100 ns, '0' after 200 ns;
    ROR_tb <= '1' after 200 ns, '0' after 250 ns;
    ASR_tb <= '1' after 250 ns, '0' after 300 ns;

    din_tb <= dout_tb after 50 ns; 
    shift_val_tb <= "00001" after 50 ns, "00101" after 100 ns, "00100" after 150 ns,
                    "00011" after 200 ns, "01001" after 250 ns, "10011" after 300 ns,
                    "00000" after 350 ns;
                      


END behavior;

Shifter/shifter.vcd
$date
  Fri Oct 27 15:11:51 2023
$end
$version
  GHDL v0
$end
$timescale
  1 fs
$end
$scope module standard $end
$upscope $end
$scope module std_logic_1164 $end
$upscope $end
$scope module tb_shifter $end
$var reg 1 ! lsl_tb $end
$var reg 1 " lsr_tb $end
$var reg 1 # asr_tb $end
$var reg 1 $ ror_tb $end
$var reg 1 % rrx_tb $end
$var reg 5 & shift_val_tb[4:0] $end
$var reg 32 ' din_tb[31:0] $end
$var reg 1 ( cin_tb $end
$var reg 32 ) dout_tb[31:0] $end
$var reg 1 * cout_tb $end
$var reg 1 + vdd_tb $end
$var reg 1 , vss_tb $end
$scope module uut $end
$var reg 1 - shift_lsl $end
$var reg 1 . shift_lsr $end
$var reg 1 / shift_asr $end
$var reg 1 0 shift_ror $end
$var reg 1 1 shift_rrx $end
$var reg 5 2 shift_val[4:0] $end
$var reg 32 3 din[31:0] $end
$var reg 1 4 cin $end
$var reg 32 5 dout[31:0] $end
$var reg 1 6 cout $end
$var reg 1 7 vdd $end
$var reg 1 8 vss $end
$var reg 32 9 dout_s1[31:0] $end
$var reg 1 : cout_s1 $end
$var reg 32 ; dout_s2[31:0] $end
$var reg 1 < cout_s2 $end
$var reg 32 = dout_s4[31:0] $end
$var reg 1 > cout_s4 $end
$var reg 32 ? dout_s8[31:0] $end
$var reg 1 @ cout_s8 $end
$var reg 32 A dout_s16[31:0] $end
$var reg 1 B cout_s16 $end
$upscope $end
$upscope $end
$enddefinitions $end
#0
0!
0"
0#
0$
0%
b00000 &
b00000011111111110000111110000000 '
0(
b00000011111111110000111110000000 )
0*
0+
0,
0-
0.
0/
00
01
b00000 2
b00000011111111110000111110000000 3
04
b00000011111111110000111110000000 5
06
07
08
b00000011111111110000111110000000 9
0:
b00000011111111110000111110000000 ;
0<
b00000011111111110000111110000000 =
0>
b00000011111111110000111110000000 ?
0@
b00000011111111110000111110000000 A
0B
#50000000
1!
b00001 &
b00000111111111100001111100000000 )
1-
b00001 2
b00000111111111100001111100000000 5
b00000111111111100001111100000000 9
b00000111111111100001111100000000 ;
b00000111111111100001111100000000 =
b00000111111111100001111100000000 ?
b00000111111111100001111100000000 A
#100000000
0!
1"
b00101 &
b00000111111111100001111100000000 '
b00000000001111111111000011111000 )
0-
1.
b00101 2
b00000111111111100001111100000000 3
b00000000001111111111000011111000 5
b00000011111111110000111110000000 9
b00000011111111110000111110000000 ;
b00000000001111111111000011111000 =
b00000000001111111111000011111000 ?
b00000000001111111111000011111000 A
#150000000
b00100 &
b00000000001111111111000011111000 '
b00000000000000111111111100001111 )
1*
b00100 2
b00000000001111111111000011111000 3
b00000000000000111111111100001111 5
16
b00000000001111111111000011111000 9
b00000000001111111111000011111000 ;
b00000000000000111111111100001111 =
1>
b00000000000000111111111100001111 ?
1@
b00000000000000111111111100001111 A
1B
#200000000
0"
1$
b00011 &
b00000000000000111111111100001111 '
b11100000000000000111111111100001 )
1*
0.
10
b00011 2
b00000000000000111111111100001111 3
b11100000000000000111111111100001 5
16
b10000000000000011111111110000111 9
1:
b11100000000000000111111111100001 ;
1<
b11100000000000000111111111100001 =
1>
b11100000000000000111111111100001 ?
1@
b11100000000000000111111111100001 A
1B
#250000000
1#
0$
b01001 &
b11100000000000000111111111100001 '
b11111111111100000000000000111111 )
1/
00
b01001 2
b11100000000000000111111111100001 3
b11111111111100000000000000111111 5
b11110000000000000011111111110000 9
b11110000000000000011111111110000 ;
b11110000000000000011111111110000 =
b11111111111100000000000000111111 ?
b11111111111100000000000000111111 A
#300000000
1!
0#
b10011 &
b11111111111100000000000000111111 '
b00000001111110000000000000000000 )
0*
1-
0/
b10011 2
b11111111111100000000000000111111 3
b00000001111110000000000000000000 5
06
b11111111111000000000000001111110 9
b11111111100000000000000111111000 ;
b11111111100000000000000111111000 =
b11111111100000000000000111111000 ?
b00000001111110000000000000000000 A
0B
#350000000
0!
b00000 &
b00000001111110000000000000000000 '
b00000001111110000000000000000000 )
0*
0-
b00000 2
b00000001111110000000000000000000 3
b00000001111110000000000000000000 5
06
b00000001111110000000000000000000 9
0:
b00000001111110000000000000000000 ;
0<
b00000001111110000000000000000000 =
0>
b00000001111110000000000000000000 ?
0@
b00000001111110000000000000000000 A
0B
